txt2tmx/__init__.py
txt2tmx/__main__.py
txt2tmx/txt2tmx.py
txt2tmx-1.0.0.dist-info/LICENSE.txt
txt2tmx-1.0.0.dist-info/METADATA
txt2tmx-1.0.0.dist-info/WHEEL
txt2tmx-1.0.0.dist-info/entry_points.txt
txt2tmx-1.0.0.dist-info/top_level.txt
txt2tmx-1.0.0.dist-info/RECORD
