Metadata-Version: 2.1
Name: txt2tmx
Version: 1.0.0
Summary: Txt-to-tmx file converter.
Home-page: https://github.com/AlexSkrn/txt2tmx
Author: AlexSkrn
Author-email: alex.g.skrn@gmail.com
License: MIT
Keywords: txt-to-tmx converter,line-to-line alignment
Platform: UNKNOWN
Classifier: License :: OSI Approved :: MIT License
Classifier: Programming Language :: Python
Classifier: Programming Language :: Python :: 3
Requires-Python: >=3.6.0
License-File: LICENSE.txt
Requires-Dist: setuptools (>=47.1.1)
Requires-Dist: wheel (>=0.34.2)
